wdb/__init__.py
wdb/__main__.py
wdb/_compat.py
wdb/breakpoint.py
wdb/ext.py
wdb/state.py
wdb/ui.py
wdb/utils.py
qwdb-3.3.1.dist-info/METADATA
qwdb-3.3.1.dist-info/WHEEL
qwdb-3.3.1.dist-info/entry_points.txt
qwdb-3.3.1.dist-info/top_level.txt
qwdb-3.3.1.dist-info/RECORD
